pykmindex/__init__.py
pykmindex/query.py
pykmindex/server.py
pykmindex-0.2.2.dist-info/METADATA
pykmindex-0.2.2.dist-info/WHEEL
pykmindex-0.2.2.dist-info/RECORD
